[ { "pid": 0, "total_memory": 174408, "code_memory": 44, "heap_memory": 23612, "stack_memory": 1040, "total_pages": 4, "code_pages": 0, "heap_pages": 0, "stack_pages": 0 }, { "pid": 0, "total_memory": 174408, "code_memory": 44, "heap_memory": 23612, "stack_memory": 1040, "total_pages": 4, "code_pages": 0, "heap_pages": 0, "stack_pages": 0 }, { "pid": 0, "total_memory": 174408, "code_memory": 44, "heap_memory": 23612, "stack_memory": 1040, "total_pages": 4, "code_pages": 0, "heap_pages": 0, "stack_pages": 0 }, { "pid": 0, "total_memory": 174408, "code_memory": 44, "heap_memory": 23612, "stack_memory": 1040, "total_pages": 4, "code_pages": 0, "heap_pages": 0, "stack_pages": 0 }, { "pid": 0, "total_memory": 174408, "code_memory": 44, "heap_memory": 23612, "stack_memory": 1040, "total_pages": 4, "code_pages": 0, "heap_pages": 0, "stack_pages": 0 }, { "pid": 0, "total_memory": 174408, "code_memory": 44, "heap_memory": 23612, "stack_memory": 1040, "total_pages": 4, "code_pages": 0, "heap_pages": 0, "stack_pages": 0 }, { "pid": 0, "total_memory": 174408, "code_memory": 44, "heap_memory": 23612, "stack_memory": 1040, "total_pages": 4, "code_pages": 0, "heap_pages": 0, "stack_pages": 0 }, { "pid": 0, "total_memory": 174408, "code_memory": 44, "heap_memory": 23612, "stack_memory": 1040, "total_pages": 4, "code_pages": 0, "heap_pages": 0, "stack_pages": 0 }, { "pid": 0, "total_memory": 174408, "code_memory": 44, "heap_memory": 23612, "stack_memory": 1040, "total_pages": 4, "code_pages": 0, "heap_pages": 0, "stack_pages": 0 }, { "pid": 0, "total_memory": 174408, "code_memory": 44, "heap_memory": 23612, "stack_memory": 1040, "total_pages": 4, "code_pages": 0, "heap_pages": 0, "stack_pages": 0 }, { "pid": 0, "total_memory": 174408, "code_memory": 44, "heap_memory": 23612, "stack_memory": 1040, "total_pages": 4, "code_pages": 0, "heap_pages": 0, "stack_pages": 0 }, { "pid": 0, "total_memory": 174408, "code_memory": 44, "heap_memory": 23612, "stack_memory": 1040, "total_pages": 4, "code_pages": 0, "heap_pages": 0, "stack_pages": 0 }, { "pid": 0, "total_memory": 174408, "code_memory": 44, "heap_memory": 23612, "stack_memory": 1040, "total_pages": 4, "code_pages": 0, "heap_pages": 0, "stack_pages": 0 }, { "pid": 0, "total_memory": 174408, "code_memory": 44, "heap_memory": 23612, "stack_memory": 1040, "total_pages": 4, "code_pages": 0, "heap_pages": 0, "stack_pages": 0 }, { "pid": 0, "total_memory": 174408, "code_memory": 44, "heap_memory": 23612, "stack_memory": 1040, "total_pages": 4, "code_pages": 0, "heap_pages": 0, "stack_pages": 0 }, { "pid": 0, "total_memory": 174408, "code_memory": 44, "heap_memory": 23612, "stack_memory": 1040, "total_pages": 4, "code_pages": 0, "heap_pages": 0, "stack_pages": 0 }, { "pid": 0, "total_memory": 174408, "code_memory": 44, "heap_memory": 23612, "stack_memory": 1040, "total_pages": 4, "code_pages": 0, "heap_pages": 0, "stack_pages": 0 }, { "pid": 0, "total_memory": 174408, "code_memory": 44, "heap_memory": 23612, "stack_memory": 1040, "total_pages": 4, "code_pages": 0, "heap_pages": 0, "stack_pages": 0 }, { "pid": 0, "total_memory": 174408, "code_memory": 44, "heap_memory": 23612, "stack_memory": 1040, "total_pages": 4, "code_pages": 0, "heap_pages": 0, "stack_pages": 0 }, { "pid": 0, "total_memory": 174408, "code_memory": 44, "heap_memory": 23612, "stack_memory": 1040, "total_pages": 4, "code_pages": 0, "heap_pages": 0, "stack_pages": 0 }, { "pid": 0, "total_memory": 174408, "code_memory": 44, "heap_memory": 23612, "stack_memory": 1040, "total_pages": 4, "code_pages": 0, "heap_pages": 0, "stack_pages": 0 }, { "pid": 0, "total_memory": 174408, "code_memory": 44, "heap_memory": 23612, "stack_memory": 1040, "total_pages": 4, "code_pages": 0, "heap_pages": 0, "stack_pages": 0 }, { "pid": 0, "total_memory": 174408, "code_memory": 44, "heap_memory": 23612, "stack_memory": 1040, "total_pages": 4, "code_pages": 0, "heap_pages": 0, "stack_pages": 0 }, { "pid": 0, "total_memory": 174408, "code_memory": 44, "heap_memory": 23612, "stack_memory": 1040, "total_pages": 4, "code_pages": 0, "heap_pages": 0, "stack_pages": 0 }, { "pid": 0, "total_memory": 174408, "code_memory": 44, "heap_memory": 23612, "stack_memory": 1040, "total_pages": 4, "code_pages": 0, "heap_pages": 0, "stack_pages": 0 }, { "pid": 0, "total_memory": 174408, "code_memory": 44, "heap_memory": 23612, "stack_memory": 1040, "total_pages": 4, "code_pages": 0, "heap_pages": 0, "stack_pages": 0 }, { "pid": 0, "total_memory": 174408, "code_memory": 44, "heap_memory": 23612, "stack_memory": 1040, "total_pages": 4, "code_pages": 0, "heap_pages": 0, "stack_pages": 0 }, { "pid": 0, "total_memory": 174408, "code_memory": 44, "heap_memory": 23612, "stack_memory": 1040, "total_pages": 4, "code_pages": 0, "heap_pages": 0, "stack_pages": 0 }, { "pid": 0, "total_memory": 174408, "code_memory": 44, "heap_memory": 23612, "stack_memory": 1040, "total_pages": 4, "code_pages": 0, "heap_pages": 0, "stack_pages": 0 }, { "pid": 0, "total_memory": 174408, "code_memory": 44, "heap_memory": 23612, "stack_memory": 1040, "total_pages": 4, "code_pages": 0, "heap_pages": 0, "stack_pages": 0 }, { "pid": 0, "total_memory": 174408, "code_memory": 44, "heap_memory": 23612, "stack_memory": 1040, "total_pages": 4, "code_pages": 0, "heap_pages": 0, "stack_pages": 0 }, { "pid": 0, "total_memory": 174408, "code_memory": 44, "heap_memory": 23612, "stack_memory": 1040, "total_pages": 4, "code_pages": 0, "heap_pages": 0, "stack_pages": 0 }, { "pid": 0, "total_memory": 174408, "code_memory": 44, "heap_memory": 23612, "stack_memory": 1040, "total_pages": 4, "code_pages": 0, "heap_pages": 0, "stack_pages": 0 }, { "pid": 0, "total_memory": 174408, "code_memory": 44, "heap_memory": 23612, "stack_memory": 1040, "total_pages": 4, "code_pages": 0, "heap_pages": 0, "stack_pages": 0 }, { "pid": 0, "total_memory": 174408, "code_memory": 44, "heap_memory": 23612, "stack_memory": 1040, "total_pages": 4, "code_pages": 0, "heap_pages": 0, "stack_pages": 0 }, { "pid": 0, "total_memory": 174408, "code_memory": 44, "heap_memory": 23612, "stack_memory": 1040, "total_pages": 4, "code_pages": 0, "heap_pages": 0, "stack_pages": 0 }, { "pid": 0, "total_memory": 174408, "code_memory": 44, "heap_memory": 23612, "stack_memory": 1040, "total_pages": 4, "code_pages": 0, "heap_pages": 0, "stack_pages": 0 }, { "pid": 0, "total_memory": 174408, "code_memory": 44, "heap_memory": 23612, "stack_memory": 1040, "total_pages": 4, "code_pages": 0, "heap_pages": 0, "stack_pages": 0 }, { "pid": 0, "total_memory": 174408, "code_memory": 44, "heap_memory": 23612, "stack_memory": 1040, "total_pages": 4, "code_pages": 0, "heap_pages": 0, "stack_pages": 0 }, { "pid": 0, "total_memory": 174408, "code_memory": 44, "heap_memory": 23612, "stack_memory": 1040, "total_pages": 4, "code_pages": 0, "heap_pages": 0, "stack_pages": 0 }, { "pid": 0, "total_memory": 174408, "code_memory": 44, "heap_memory": 23612, "stack_memory": 1040, "total_pages": 4, "code_pages": 0, "heap_pages": 0, "stack_pages": 0 }, { "pid": 0, "total_memory": 174408, "code_memory": 44, "heap_memory": 23612, "stack_memory": 1040, "total_pages": 4, "code_pages": 0, "heap_pages": 0, "stack_pages": 0 }, { "pid": 0, "total_memory": 174408, "code_memory": 44, "heap_memory": 23612, "stack_memory": 1040, "total_pages": 4, "code_pages": 0, "heap_pages": 0, "stack_pages": 0 }, { "pid": 0, "total_memory": 174408, "code_memory": 44, "heap_memory": 23612, "stack_memory": 1040, "total_pages": 4, "code_pages": 0, "heap_pages": 0, "stack_pages": 0 }, { "pid": 0, "total_memory": 174408, "code_memory": 44, "heap_memory": 23612, "stack_memory": 1040, "total_pages": 4, "code_pages": 0, "heap_pages": 0, "stack_pages": 0 }, { "pid": 0, "total_memory": 174408, "code_memory": 44, "heap_memory": 23612, "stack_memory": 1040, "total_pages": 4, "code_pages": 0, "heap_pages": 0, "stack_pages": 0 }, { "pid": 0, "total_memory": 174408, "code_memory": 44, "heap_memory": 23612, "stack_memory": 1040, "total_pages": 4, "code_pages": 0, "heap_pages": 0, "stack_pages": 0 }, { "pid": 0, "total_memory": 174408, "code_memory": 44, "heap_memory": 23612, "stack_memory": 1040, "total_pages": 4, "code_pages": 0, "heap_pages": 0, "stack_pages": 0 }, { "pid": 0, "total_memory": 174408, "code_memory": 44, "heap_memory": 23612, "stack_memory": 1040, "total_pages": 4, "code_pages": 0, "heap_pages": 0, "stack_pages": 0 }, { "pid": 0, "total_memory": 174408, "code_memory": 44, "heap_memory": 23612, "stack_memory": 1040, "total_pages": 4, "code_pages": 0, "heap_pages": 0, "stack_pages": 0 }, { "pid": 0, "total_memory": 174408, "code_memory": 44, "heap_memory": 23612, "stack_memory": 1040, "total_pages": 4, "code_pages": 0, "heap_pages": 0, "stack_pages": 0 }, { "pid": 0, "total_memory": 174408, "code_memory": 44, "heap_memory": 23612, "stack_memory": 1040, "total_pages": 4, "code_pages": 0, "heap_pages": 0, "stack_pages": 0 }, { "pid": 0, "total_memory": 174408, "code_memory": 44, "heap_memory": 23612, "stack_memory": 1040, "total_pages": 4, "code_pages": 0, "heap_pages": 0, "stack_pages": 0 }, { "pid": 0, "total_memory": 174408, "code_memory": 44, "heap_memory": 23612, "stack_memory": 1040, "total_pages": 4, "code_pages": 0, "heap_pages": 0, "stack_pages": 0 }, { "pid": 0, "total_memory": 174408, "code_memory": 44, "heap_memory": 23612, "stack_memory": 1040, "total_pages": 4, "code_pages": 0, "heap_pages": 0, "stack_pages": 0 }, { "pid": 0, "total_memory": 174408, "code_memory": 44, "heap_memory": 23612, "stack_memory": 1040, "total_pages": 4, "code_pages": 0, "heap_pages": 0, "stack_pages": 0 }, { "pid": 0, "total_memory": 174408, "code_memory": 44, "heap_memory": 23612, "stack_memory": 1040, "total_pages": 4, "code_pages": 0, "heap_pages": 0, "stack_pages": 0 }, { "pid": 0, "total_memory": 174408, "code_memory": 44, "heap_memory": 23612, "stack_memory": 1040, "total_pages": 4, "code_pages": 0, "heap_pages": 0, "stack_pages": 0 }, { "pid": 0, "total_memory": 174408, "code_memory": 44, "heap_memory": 23612, "stack_memory": 1040, "total_pages": 4, "code_pages": 0, "heap_pages": 0, "stack_pages": 0 }, { "pid": 0, "total_memory": 174408, "code_memory": 44, "heap_memory": 23612, "stack_memory": 1040, "total_pages": 4, "code_pages": 0, "heap_pages": 0, "stack_pages": 0 }, { "pid": 0, "total_memory": 174408, "code_memory": 44, "heap_memory": 23612, "stack_memory": 1040, "total_pages": 4, "code_pages": 0, "heap_pages": 0, "stack_pages": 0 }, { "pid": 0, "total_memory": 174408, "code_memory": 44, "heap_memory": 23612, "stack_memory": 1040, "total_pages": 4, "code_pages": 0, "heap_pages": 0, "stack_pages": 0 }, { "pid": 0, "total_memory": 174408, "code_memory": 44, "heap_memory": 23612, "stack_memory": 1040, "total_pages": 4, "code_pages": 0, "heap_pages": 0, "stack_pages": 0 }, { "pid": 0, "total_memory": 174408, "code_memory": 44, "heap_memory": 23612, "stack_memory": 1040, "total_pages": 4, "code_pages": 0, "heap_pages": 0, "stack_pages": 0 }, { "pid": 0, "total_memory": 174408, "code_memory": 44, "heap_memory": 23612, "stack_memory": 1040, "total_pages": 4, "code_pages": 0, "heap_pages": 0, "stack_pages": 0 }, { "pid": 0, "total_memory": 174408, "code_memory": 44, "heap_memory": 23612, "stack_memory": 1040, "total_pages": 4, "code_pages": 0, "heap_pages": 0, "stack_pages": 0 }, { "pid": 0, "total_memory": 174408, "code_memory": 44, "heap_memory": 23612, "stack_memory": 1040, "total_pages": 4, "code_pages": 0, "heap_pages": 0, "stack_pages": 0 }, { "pid": 0, "total_memory": 174408, "code_memory": 44, "heap_memory": 23612, "stack_memory": 1040, "total_pages": 4, "code_pages": 0, "heap_pages": 0, "stack_pages": 0 }, { "pid": 0, "total_memory": 174408, "code_memory": 44, "heap_memory": 23612, "stack_memory": 1040, "total_pages": 4, "code_pages": 0, "heap_pages": 0, "stack_pages": 0 }, { "pid": 0, "total_memory": 174408, "code_memory": 44, "heap_memory": 23612, "stack_memory": 1040, "total_pages": 4, "code_pages": 0, "heap_pages": 0, "stack_pages": 0 }, { "pid": 0, "total_memory": 174408, "code_memory": 44, "heap_memory": 23612, "stack_memory": 1040, "total_pages": 4, "code_pages": 0, "heap_pages": 0, "stack_pages": 0 }, { "pid": 0, "total_memory": 174408, "code_memory": 44, "heap_memory": 23612, "stack_memory": 1040, "total_pages": 4, "code_pages": 0, "heap_pages": 0, "stack_pages": 0 }, { "pid": 0, "total_memory": 174408, "code_memory": 44, "heap_memory": 23612, "stack_memory": 1040, "total_pages": 4, "code_pages": 0, "heap_pages": 0, "stack_pages": 0 }, { "pid": 0, "total_memory": 174408, "code_memory": 44, "heap_memory": 23612, "stack_memory": 1040, "total_pages": 4, "code_pages": 0, "heap_pages": 0, "stack_pages": 0 }, { "pid": 0, "total_memory": 174408, "code_memory": 44, "heap_memory": 23612, "stack_memory": 1040, "total_pages": 4, "code_pages": 0, "heap_pages": 0, "stack_pages": 0 }, { "pid": 0, "total_memory": 174408, "code_memory": 44, "heap_memory": 23612, "stack_memory": 1040, "total_pages": 4, "code_pages": 0, "heap_pages": 0, "stack_pages": 0 }, { "pid": 0, "total_memory": 174408, "code_memory": 44, "heap_memory": 23612, "stack_memory": 1040, "total_pages": 4, "code_pages": 0, "heap_pages": 0, "stack_pages": 0 }, { "pid": 0, "total_memory": 174408, "code_memory": 44, "heap_memory": 23612, "stack_memory": 1040, "total_pages": 4, "code_pages": 0, "heap_pages": 0, "stack_pages": 0 }, { "pid": 0, "total_memory": 174408, "code_memory": 44, "heap_memory": 23612, "stack_memory": 1040, "total_pages": 4, "code_pages": 0, "heap_pages": 0, "stack_pages": 0 }, { "pid": 0, "total_memory": 174408, "code_memory": 44, "heap_memory": 23612, "stack_memory": 1040, "total_pages": 4, "code_pages": 0, "heap_pages": 0, "stack_pages": 0 }, { "pid": 0, "total_memory": 174408, "code_memory": 44, "heap_memory": 23612, "stack_memory": 1040, "total_pages": 4, "code_pages": 0, "heap_pages": 0, "stack_pages": 0 }, { "pid": 0, "total_memory": 174408, "code_memory": 44, "heap_memory": 23612, "stack_memory": 1040, "total_pages": 4, "code_pages": 0, "heap_pages": 0, "stack_pages": 0 }, { "pid": 0, "total_memory": 174408, "code_memory": 44, "heap_memory": 23612, "stack_memory": 1040, "total_pages": 4, "code_pages": 0, "heap_pages": 0, "stack_pages": 0 }, { "pid": 0, "total_memory": 174408, "code_memory": 44, "heap_memory": 23612, "stack_memory": 1040, "total_pages": 4, "code_pages": 0, "heap_pages": 0, "stack_pages": 0 }, { "pid": 0, "total_memory": 174408, "code_memory": 44, "heap_memory": 23612, "stack_memory": 1040, "total_pages": 4, "code_pages": 0, "heap_pages": 0, "stack_pages": 0 }, { "pid": 0, "total_memory": 174408, "code_memory": 44, "heap_memory": 23612, "stack_memory": 1040, "total_pages": 4, "code_pages": 0, "heap_pages": 0, "stack_pages": 0 }, { "pid": 0, "total_memory": 174408, "code_memory": 44, "heap_memory": 23612, "stack_memory": 1040, "total_pages": 4, "code_pages": 0, "heap_pages": 0, "stack_pages": 0 }, { "pid": 0, "total_memory": 174408, "code_memory": 44, "heap_memory": 23612, "stack_memory": 1040, "total_pages": 4, "code_pages": 0, "heap_pages": 0, "stack_pages": 0 }, { "pid": 0, "total_memory": 174408, "code_memory": 44, "heap_memory": 23612, "stack_memory": 1040, "total_pages": 4, "code_pages": 0, "heap_pages": 0, "stack_pages": 0 }, { "pid": 0, "total_memory": 174408, "code_memory": 44, "heap_memory": 23612, "stack_memory": 1040, "total_pages": 4, "code_pages": 0, "heap_pages": 0, "stack_pages": 0 }, { "pid": 0, "total_memory": 174408, "code_memory": 44, "heap_memory": 23612, "stack_memory": 1040, "total_pages": 4, "code_pages": 0, "heap_pages": 0, "stack_pages": 0 }, { "pid": 0, "total_memory": 174408, "code_memory": 44, "heap_memory": 23612, "stack_memory": 1040, "total_pages": 4, "code_pages": 0, "heap_pages": 0, "stack_pages": 0 }, { "pid": 0, "total_memory": 174408, "code_memory": 44, "heap_memory": 23612, "stack_memory": 1040, "total_pages": 4, "code_pages": 0, "heap_pages": 0, "stack_pages": 0 }, { "pid": 0, "total_memory": 174408, "code_memory": 44, "heap_memory": 23612, "stack_memory": 1040, "total_pages": 4, "code_pages": 0, "heap_pages": 0, "stack_pages": 0 }, { "pid": 0, "total_memory": 174408, "code_memory": 44, "heap_memory": 23612, "stack_memory": 1040, "total_pages": 4, "code_pages": 0, "heap_pages": 0, "stack_pages": 0 }, { "pid": 0, "total_memory": 174408, "code_memory": 44, "heap_memory": 23612, "stack_memory": 1040, "total_pages": 4, "code_pages": 0, "heap_pages": 0, "stack_pages": 0 }, { "pid": 0, "total_memory": 174408, "code_memory": 44, "heap_memory": 23612, "stack_memory": 1040, "total_pages": 4, "code_pages": 0, "heap_pages": 0, "stack_pages": 0 }, { "pid": 0, "total_memory": 174408, "code_memory": 44, "heap_memory": 23612, "stack_memory": 1040, "total_pages": 4, "code_pages": 0, "heap_pages": 0, "stack_pages": 0 }, { "pid": 0, "total_memory": 174408, "code_memory": 44, "heap_memory": 23612, "stack_memory": 1040, "total_pages": 4, "code_pages": 0, "heap_pages": 0, "stack_pages": 0 }, { "pid": 0, "total_memory": 174408, "code_memory": 44, "heap_memory": 23612, "stack_memory": 1040, "total_pages": 4, "code_pages": 0, "heap_pages": 0, "stack_pages": 0 }, { "pid": 0, "total_memory": 174408, "code_memory": 44, "heap_memory": 23612, "stack_memory": 1040, "total_pages": 4, "code_pages": 0, "heap_pages": 0, "stack_pages": 0 }, { "pid": 0, "total_memory": 174408, "code_memory": 44, "heap_memory": 23612, "stack_memory": 1040, "total_pages": 4, "code_pages": 0, "heap_pages": 0, "stack_pages": 0 }, { "pid": 0, "total_memory": 174408, "code_memory": 44, "heap_memory": 23612, "stack_memory": 1040, "total_pages": 4, "code_pages": 0, "heap_pages": 0, "stack_pages": 0 }, { "pid": 0, "total_memory": 174408, "code_memory": 44, "heap_memory": 23612, "stack_memory": 1040, "total_pages": 4, "code_pages": 0, "heap_pages": 0, "stack_pages": 0 }, { "pid": 0, "total_memory": 174408, "code_memory": 44, "heap_memory": 23612, "stack_memory": 1040, "total_pages": 4, "code_pages": 0, "heap_pages": 0, "stack_pages": 0 }, { "pid": 0, "total_memory": 174408, "code_memory": 44, "heap_memory": 23612, "stack_memory": 1040, "total_pages": 4, "code_pages": 0, "heap_pages": 0, "stack_pages": 0 }, { "pid": 0, "total_memory": 174408, "code_memory": 44, "heap_memory": 23612, "stack_memory": 1040, "total_pages": 4, "code_pages": 0, "heap_pages": 0, "stack_pages": 0 }, { "pid": 0, "total_memory": 174408, "code_memory": 44, "heap_memory": 23612, "stack_memory": 1040, "total_pages": 4, "code_pages": 0, "heap_pages": 0, "stack_pages": 0 }, { "pid": 0, "total_memory": 174408, "code_memory": 44, "heap_memory": 23612, "stack_memory": 1040, "total_pages": 4, "code_pages": 0, "heap_pages": 0, "stack_pages": 0 }, { "pid": 0, "total_memory": 174408, "code_memory": 44, "heap_memory": 23612, "stack_memory": 1040, "total_pages": 4, "code_pages": 0, "heap_pages": 0, "stack_pages": 0 }, { "pid": 0, "total_memory": 174408, "code_memory": 44, "heap_memory": 23612, "stack_memory": 1040, "total_pages": 4, "code_pages": 0, "heap_pages": 0, "stack_pages": 0 }, { "pid": 0, "total_memory": 174408, "code_memory": 44, "heap_memory": 23612, "stack_memory": 1040, "total_pages": 4, "code_pages": 0, "heap_pages": 0, "stack_pages": 0 }, { "pid": 0, "total_memory": 174408, "code_memory": 44, "heap_memory": 23612, "stack_memory": 1040, "total_pages": 4, "code_pages": 0, "heap_pages": 0, "stack_pages": 0 }, { "pid": 0, "total_memory": 174408, "code_memory": 44, "heap_memory": 23612, "stack_memory": 1040, "total_pages": 4, "code_pages": 0, "heap_pages": 0, "stack_pages": 0 }, { "pid": 0, "total_memory": 174408, "code_memory": 44, "heap_memory": 23612, "stack_memory": 1040, "total_pages": 4, "code_pages": 0, "heap_pages": 0, "stack_pages": 0 }, { "pid": 0, "total_memory": 174408, "code_memory": 44, "heap_memory": 23612, "stack_memory": 1040, "total_pages": 4, "code_pages": 0, "heap_pages": 0, "stack_pages": 0 }, { "pid": 0, "total_memory": 174408, "code_memory": 44, "heap_memory": 23612, "stack_memory": 1040, "total_pages": 4, "code_pages": 0, "heap_pages": 0, "stack_pages": 0 }, { "pid": 0, "total_memory": 99852, "code_memory": 104, "heap_memory": 18344, "stack_memory": 132, "total_pages": 4, "code_pages": 0, "heap_pages": 0, "stack_pages": 0 }, { "pid": 0, "total_memory": 35948, "code_memory": 264, "heap_memory": 4044, "stack_memory": 132, "total_pages": 4, "code_pages": 0, "heap_pages": 0, "stack_pages": 0 }, { "pid": 0, "total_memory": 35948, "code_memory": 264, "heap_memory": 4044, "stack_memory": 132, "total_pages": 4, "code_pages": 0, "heap_pages": 0, "stack_pages": 0 }, { "pid": 0, "total_memory": 35948, "code_memory": 264, "heap_memory": 4044, "stack_memory": 132, "total_pages": 4, "code_pages": 0, "heap_pages": 0, "stack_pages": 0 }, { "pid": 0, "total_memory": 35948, "code_memory": 264, "heap_memory": 4044, "stack_memory": 132, "total_pages": 4, "code_pages": 0, "heap_pages": 0, "stack_pages": 0 }, { "pid": 0, "total_memory": 35948, "code_memory": 264, "heap_memory": 4044, "stack_memory": 132, "total_pages": 4, "code_pages": 0, "heap_pages": 0, "stack_pages": 0 }, { "pid": 0, "total_memory": 35948, "code_memory": 264, "heap_memory": 4044, "stack_memory": 132, "total_pages": 4, "code_pages": 0, "heap_pages": 0, "stack_pages": 0 }, { "pid": 0, "total_memory": 16656, "code_memory": 28, "heap_memory": 772, "stack_memory": 132, "total_pages": 4, "code_pages": 0, "heap_pages": 0, "stack_pages": 0 }, { "pid": 0, "total_memory": 24992, "code_memory": 344, "heap_memory": 5336, "stack_memory": 132, "total_pages": 4, "code_pages": 0, "heap_pages": 0, "stack_pages": 0 }, { "pid": 0, "total_memory": 16352, "code_memory": 8, "heap_memory": 508, "stack_memory": 132, "total_pages": 4, "code_pages": 0, "heap_pages": 0, "stack_pages": 0 }, { "pid": 0, "total_memory": 17896, "code_memory": 76, "heap_memory": 8584, "stack_memory": 132, "total_pages": 4, "code_pages": 0, "heap_pages": 0, "stack_pages": 0 }, { "pid": 0, "total_memory": 17896, "code_memory": 76, "heap_memory": 8584, "stack_memory": 132, "total_pages": 4, "code_pages": 0, "heap_pages": 0, "stack_pages": 0 }, { "pid": 0, "total_memory": 17896, "code_memory": 76, "heap_memory": 8584, "stack_memory": 132, "total_pages": 4, "code_pages": 0, "heap_pages": 0, "stack_pages": 0 }, { "pid": 0, "total_memory": 9476, "code_memory": 84, "heap_memory": 928, "stack_memory": 132, "total_pages": 4, "code_pages": 0, "heap_pages": 0, "stack_pages": 0 }, { "pid": 0, "total_memory": 11276, "code_memory": 148, "heap_memory": 4780, "stack_memory": 132, "total_pages": 4, "code_pages": 0, "heap_pages": 0, "stack_pages": 0 }, { "pid": 0, "total_memory": 7604, "code_memory": 80, "heap_memory": 1004, "stack_memory": 132, "total_pages": 4, "code_pages": 0, "heap_pages": 0, "stack_pages": 0 }, { "pid": 0, "total_memory": 8704, "code_memory": 844, "heap_memory": 532, "stack_memory": 132, "total_pages": 4, "code_pages": 0, "heap_pages": 0, "stack_pages": 0 }, { "pid": 0, "total_memory": 390072, "code_memory": 9116, "heap_memory": 50308, "stack_memory": 132, "total_pages": 4, "code_pages": 0, "heap_pages": 0, "stack_pages": 0 }, { "pid": 0, "total_memory": 228984, "code_memory": 8, "heap_memory": 25384, "stack_memory": 132, "total_pages": 4, "code_pages": 0, "heap_pages": 0, "stack_pages": 0 }, { "pid": 0, "total_memory": 3128, "code_memory": 56, "heap_memory": 748, "stack_memory": 132, "total_pages": 4, "code_pages": 0, "heap_pages": 0, "stack_pages": 0 }, { "pid": 0, "total_memory": 2802020, "code_memory": 68, "heap_memory": 59416, "stack_memory": 132, "total_pages": 4, "code_pages": 0, "heap_pages": 0, "stack_pages": 0 }, { "pid": 0, "total_memory": 451092, "code_memory": 32, "heap_memory": 25688, "stack_memory": 132, "total_pages": 4, "code_pages": 0, "heap_pages": 0, "stack_pages": 0 }, { "pid": 0, "total_memory": 21376, "code_memory": 28, "heap_memory": 16624, "stack_memory": 132, "total_pages": 4, "code_pages": 0, "heap_pages": 0, "stack_pages": 0 }, { "pid": 0, "total_memory": 525212, "code_memory": 80, "heap_memory": 34540, "stack_memory": 132, "total_pages": 4, "code_pages": 0, "heap_pages": 0, "stack_pages": 0 }, { "pid": 0, "total_memory": 448376, "code_memory": 8, "heap_memory": 25416, "stack_memory": 132, "total_pages": 4, "code_pages": 0, "heap_pages": 0, "stack_pages": 0 }, { "pid": 0, "total_memory": 52412, "code_memory": 148, "heap_memory": 35684, "stack_memory": 132, "total_pages": 4, "code_pages": 0, "heap_pages": 0, "stack_pages": 0 }, { "pid": 0, "total_memory": 16668, "code_memory": 68, "heap_memory": 712, "stack_memory": 132, "total_pages": 4, "code_pages": 0, "heap_pages": 0, "stack_pages": 0 }, { "pid": 0, "total_memory": 456148, "code_memory": 352, "heap_memory": 25752, "stack_memory": 132, "total_pages": 4, "code_pages": 0, "heap_pages": 0, "stack_pages": 0 }, { "pid": 0, "total_memory": 394204, "code_memory": 280, "heap_memory": 43824, "stack_memory": 132, "total_pages": 4, "code_pages": 0, "heap_pages": 0, "stack_pages": 0 }, { "pid": 0, "total_memory": 449444, "code_memory": 76, "heap_memory": 26284, "stack_memory": 132, "total_pages": 4, "code_pages": 0, "heap_pages": 0, "stack_pages": 0 }, { "pid": 0, "total_memory": 3520604, "code_memory": 12588, "heap_memory": 37884, "stack_memory": 132, "total_pages": 4, "code_pages": 0, "heap_pages": 0, "stack_pages": 0 }, { "pid": 0, "total_memory": 6888, "code_memory": 80, "heap_memory": 288, "stack_memory": 132, "total_pages": 4, "code_pages": 0, "heap_pages": 0, "stack_pages": 0 }, { "pid": 0, "total_memory": 465516, "code_memory": 16, "heap_memory": 26476, "stack_memory": 132, "total_pages": 4, "code_pages": 0, "heap_pages": 0, "stack_pages": 0 }, { "pid": 0, "total_memory": 465516, "code_memory": 16, "heap_memory": 26476, "stack_memory": 132, "total_pages": 4, "code_pages": 0, "heap_pages": 0, "stack_pages": 0 }, { "pid": 0, "total_memory": 4544, "code_memory": 76, "heap_memory": 208, "stack_memory": 132, "total_pages": 4, "code_pages": 0, "heap_pages": 0, "stack_pages": 0 }, { "pid": 0, "total_memory": 85540, "code_memory": 248, "heap_memory": 8972, "stack_memory": 132, "total_pages": 4, "code_pages": 0, "heap_pages": 0, "stack_pages": 0 }, { "pid": 0, "total_memory": 388488, "code_memory": 1100, "heap_memory": 42992, "stack_memory": 132, "total_pages": 4, "code_pages": 0, "heap_pages": 0, "stack_pages": 0 }, { "pid": 0, "total_memory": 1070024, "code_memory": 12, "heap_memory": 4640, "stack_memory": 132, "total_pages": 4, "code_pages": 0, "heap_pages": 0, "stack_pages": 0 }, { "pid": 0, "total_memory": 1066852, "code_memory": 16, "heap_memory": 1452, "stack_memory": 132, "total_pages": 4, "code_pages": 0, "heap_pages": 0, "stack_pages": 0 }, { "pid": 0, "total_memory": 1067036, "code_memory": 12, "heap_memory": 1468, "stack_memory": 132, "total_pages": 4, "code_pages": 0, "heap_pages": 0, "stack_pages": 0 }, { "pid": 0, "total_memory": 355096, "code_memory": 4, "heap_memory": 35944, "stack_memory": 132, "total_pages": 4, "code_pages": 0, "heap_pages": 0, "stack_pages": 0 }, { "pid": 0, "total_memory": 473384, "code_memory": 2348, "heap_memory": 28232, "stack_memory": 132, "total_pages": 4, "code_pages": 0, "heap_pages": 0, "stack_pages": 0 }, { "pid": 0, "total_memory": 247168, "code_memory": 328, "heap_memory": 7268, "stack_memory": 132, "total_pages": 4, "code_pages": 0, "heap_pages": 0, "stack_pages": 0 }, { "pid": 0, "total_memory": 270748, "code_memory": 84, "heap_memory": 41444, "stack_memory": 132, "total_pages": 4, "code_pages": 0, "heap_pages": 0, "stack_pages": 0 }, { "pid": 0, "total_memory": 2365380, "code_memory": 23512, "heap_memory": 759588, "stack_memory": 132, "total_pages": 4, "code_pages": 0, "heap_pages": 0, "stack_pages": 0 }, { "pid": 0, "total_memory": 14656, "code_memory": 1976, "heap_memory": 1248, "stack_memory": 132, "total_pages": 4, "code_pages": 0, "heap_pages": 0, "stack_pages": 0 }, { "pid": 0, "total_memory": 451712, "code_memory": 204, "heap_memory": 25780, "stack_memory": 132, "total_pages": 4, "code_pages": 0, "heap_pages": 0, "stack_pages": 0 }, { "pid": 0, "total_memory": 1499264, "code_memory": 63192, "heap_memory": 369264, "stack_memory": 132, "total_pages": 4, "code_pages": 0, "heap_pages": 0, "stack_pages": 0 }, { "pid": 0, "total_memory": 231944, "code_memory": 28, "heap_memory": 25436, "stack_memory": 132, "total_pages": 4, "code_pages": 0, "heap_pages": 0, "stack_pages": 0 }, { "pid": 0, "total_memory": 1162572, "code_memory": 176, "heap_memory": 534348, "stack_memory": 132, "total_pages": 4, "code_pages": 0, "heap_pages": 0, "stack_pages": 0 }, { "pid": 0, "total_memory": 529444, "code_memory": 108, "heap_memory": 35156, "stack_memory": 132, "total_pages": 4, "code_pages": 0, "heap_pages": 0, "stack_pages": 0 }, { "pid": 0, "total_memory": 1050808, "code_memory": 68, "heap_memory": 125360, "stack_memory": 132, "total_pages": 4, "code_pages": 0, "heap_pages": 0, "stack_pages": 0 }, { "pid": 0, "total_memory": 1050808, "code_memory": 68, "heap_memory": 125360, "stack_memory": 132, "total_pages": 4, "code_pages": 0, "heap_pages": 0, "stack_pages": 0 }, { "pid": 0, "total_memory": 534176, "code_memory": 116, "heap_memory": 35136, "stack_memory": 132, "total_pages": 4, "code_pages": 0, "heap_pages": 0, "stack_pages": 0 }, { "pid": 0, "total_memory": 22780, "code_memory": 44, "heap_memory": 3708, "stack_memory": 132, "total_pages": 4, "code_pages": 0, "heap_pages": 0, "stack_pages": 0 }, { "pid": 0, "total_memory": 176948, "code_memory": 44, "heap_memory": 23668, "stack_memory": 132, "total_pages": 4, "code_pages": 0, "heap_pages": 0, "stack_pages": 0 }, { "pid": 0, "total_memory": 455344, "code_memory": 564, "heap_memory": 26024, "stack_memory": 132, "total_pages": 4, "code_pages": 0, "heap_pages": 0, "stack_pages": 0 }, { "pid": 0, "total_memory": 374452, "code_memory": 24, "heap_memory": 17072, "stack_memory": 132, "total_pages": 4, "code_pages": 0, "heap_pages": 0, "stack_pages": 0 }, { "pid": 0, "total_memory": 1542660, "code_memory": 1636, "heap_memory": 189016, "stack_memory": 132, "total_pages": 4, "code_pages": 0, "heap_pages": 0, "stack_pages": 0 }, { "pid": 0, "total_memory": 9012, "code_memory": 84, "heap_memory": 464, "stack_memory": 132, "total_pages": 4, "code_pages": 0, "heap_pages": 0, "stack_pages": 0 }, { "pid": 0, "total_memory": 7728, "code_memory": 148, "heap_memory": 3280, "stack_memory": 132, "total_pages": 4, "code_pages": 0, "heap_pages": 0, "stack_pages": 0 }, { "pid": 0, "total_memory": 515240, "code_memory": 140, "heap_memory": 26148, "stack_memory": 132, "total_pages": 4, "code_pages": 0, "heap_pages": 0, "stack_pages": 0 }, { "pid": 0, "total_memory": 7212, "code_memory": 112, "heap_memory": 364, "stack_memory": 132, "total_pages": 4, "code_pages": 0, "heap_pages": 0, "stack_pages": 0 }, { "pid": 0, "total_memory": 306636, "code_memory": 12, "heap_memory": 33852, "stack_memory": 132, "total_pages": 4, "code_pages": 0, "heap_pages": 0, "stack_pages": 0 }, { "pid": 0, "total_memory": 8880, "code_memory": 84, "heap_memory": 332, "stack_memory": 132, "total_pages": 4, "code_pages": 0, "heap_pages": 0, "stack_pages": 0 }, { "pid": 0, "total_memory": 4892, "code_memory": 148, "heap_memory": 444, "stack_memory": 132, "total_pages": 4, "code_pages": 0, "heap_pages": 0, "stack_pages": 0 }, { "pid": 0, "total_memory": 302240, "code_memory": 8, "heap_memory": 8648, "stack_memory": 132, "total_pages": 4, "code_pages": 0, "heap_pages": 0, "stack_pages": 0 }, { "pid": 0, "total_memory": 243608, "code_memory": 28, "heap_memory": 34176, "stack_memory": 132, "total_pages": 4, "code_pages": 0, "heap_pages": 0, "stack_pages": 0 }, { "pid": 0, "total_memory": 811344, "code_memory": 140, "heap_memory": 60492, "stack_memory": 132, "total_pages": 4, "code_pages": 0, "heap_pages": 0, "stack_pages": 0 }, { "pid": 0, "total_memory": 453044, "code_memory": 16, "heap_memory": 25736, "stack_memory": 132, "total_pages": 4, "code_pages": 0, "heap_pages": 0, "stack_pages": 0 }, { "pid": 0, "total_memory": 379324, "code_memory": 24, "heap_memory": 44248, "stack_memory": 132, "total_pages": 4, "code_pages": 0, "heap_pages": 0, "stack_pages": 0 }, { "pid": 0, "total_memory": 332616, "code_memory": 4, "heap_memory": 35468, "stack_memory": 132, "total_pages": 4, "code_pages": 0, "heap_pages": 0, "stack_pages": 0 }, { "pid": 0, "total_memory": 546240, "code_memory": 12, "heap_memory": 45880, "stack_memory": 132, "total_pages": 4, "code_pages": 0, "heap_pages": 0, "stack_pages": 0 }, { "pid": 0, "total_memory": 5744800, "code_memory": 8, "heap_memory": 367752, "stack_memory": 132, "total_pages": 4, "code_pages": 0, "heap_pages": 0, "stack_pages": 0 }, { "pid": 0, "total_memory": 448300, "code_memory": 36, "heap_memory": 25380, "stack_memory": 132, "total_pages": 4, "code_pages": 0, "heap_pages": 0, "stack_pages": 0 }, { "pid": 0, "total_memory": 995688, "code_memory": 20, "heap_memory": 79572, "stack_memory": 132, "total_pages": 4, "code_pages": 0, "heap_pages": 0, "stack_pages": 0 }, { "pid": 0, "total_memory": 1432860, "code_memory": 40, "heap_memory": 86036, "stack_memory": 132, "total_pages": 4, "code_pages": 0, "heap_pages": 0, "stack_pages": 0 }, { "pid": 0, "total_memory": 342412, "code_memory": 4, "heap_memory": 45088, "stack_memory": 132, "total_pages": 4, "code_pages": 0, "heap_pages": 0, "stack_pages": 0 }, { "pid": 0, "total_memory": 1176624, "code_memory": 176, "heap_memory": 76324, "stack_memory": 132, "total_pages": 4, "code_pages": 0, "heap_pages": 0, "stack_pages": 0 }, { "pid": 0, "total_memory": 155716, "code_memory": 36, "heap_memory": 17508, "stack_memory": 132, "total_pages": 4, "code_pages": 0, "heap_pages": 0, "stack_pages": 0 }, { "pid": 0, "total_memory": 534212, "code_memory": 92, "heap_memory": 35180, "stack_memory": 132, "total_pages": 4, "code_pages": 0, "heap_pages": 0, "stack_pages": 0 }, { "pid": 0, "total_memory": 1162108, "code_memory": 24, "heap_memory": 91256, "stack_memory": 132, "total_pages": 4, "code_pages": 0, "heap_pages": 0, "stack_pages": 0 }, { "pid": 0, "total_memory": 448496, "code_memory": 40, "heap_memory": 25424, "stack_memory": 132, "total_pages": 4, "code_pages": 0, "heap_pages": 0, "stack_pages": 0 }, { "pid": 0, "total_memory": 450496, "code_memory": 40, "heap_memory": 25964, "stack_memory": 132, "total_pages": 4, "code_pages": 0, "heap_pages": 0, "stack_pages": 0 }, { "pid": 0, "total_memory": 375320, "code_memory": 28, "heap_memory": 17348, "stack_memory": 132, "total_pages": 4, "code_pages": 0, "heap_pages": 0, "stack_pages": 0 }, { "pid": 0, "total_memory": 449592, "code_memory": 44, "heap_memory": 25660, "stack_memory": 132, "total_pages": 4, "code_pages": 0, "heap_pages": 0, "stack_pages": 0 }, { "pid": 0, "total_memory": 2155072, "code_memory": 4, "heap_memory": 190148, "stack_memory": 132, "total_pages": 4, "code_pages": 0, "heap_pages": 0, "stack_pages": 0 }, { "pid": 0, "total_memory": 531792, "code_memory": 72, "heap_memory": 34044, "stack_memory": 132, "total_pages": 4, "code_pages": 0, "heap_pages": 0, "stack_pages": 0 }, { "pid": 0, "total_memory": 528064, "code_memory": 36, "heap_memory": 33788, "stack_memory": 132, "total_pages": 4, "code_pages": 0, "heap_pages": 0, "stack_pages": 0 }, { "pid": 0, "total_memory": 1048800, "code_memory": 4, "heap_memory": 179808, "stack_memory": 132, "total_pages": 4, "code_pages": 0, "heap_pages": 0, "stack_pages": 0 }, { "pid": 0, "total_memory": 3083952, "code_memory": 8, "heap_memory": 48436, "stack_memory": 132, "total_pages": 4, "code_pages": 0, "heap_pages": 0, "stack_pages": 0 }, { "pid": 0, "total_memory": 159696, "code_memory": 40, "heap_memory": 17220, "stack_memory": 132, "total_pages": 4, "code_pages": 0, "heap_pages": 0, "stack_pages": 0 }, { "pid": 0, "total_memory": 602408, "code_memory": 104, "heap_memory": 47856, "stack_memory": 132, "total_pages": 4, "code_pages": 0, "heap_pages": 0, "stack_pages": 0 }, { "pid": 0, "total_memory": 522828, "code_memory": 8, "heap_memory": 33872, "stack_memory": 132, "total_pages": 4, "code_pages": 0, "heap_pages": 0, "stack_pages": 0 }, { "pid": 0, "total_memory": 741468, "code_memory": 24, "heap_memory": 54932, "stack_memory": 132, "total_pages": 4, "code_pages": 0, "heap_pages": 0, "stack_pages": 0 }, { "pid": 0, "total_memory": 539372, "code_memory": 20, "heap_memory": 34112, "stack_memory": 132, "total_pages": 4, "code_pages": 0, "heap_pages": 0, "stack_pages": 0 }, { "pid": 0, "total_memory": 599080, "code_memory": 24, "heap_memory": 42548, "stack_memory": 132, "total_pages": 4, "code_pages": 0, "heap_pages": 0, "stack_pages": 0 }, { "pid": 0, "total_memory": 666496, "code_memory": 12, "heap_memory": 46512, "stack_memory": 132, "total_pages": 4, "code_pages": 0, "heap_pages": 0, "stack_pages": 0 }, { "pid": 0, "total_memory": 231600, "code_memory": 8, "heap_memory": 26444, "stack_memory": 132, "total_pages": 4, "code_pages": 0, "heap_pages": 0, "stack_pages": 0 }, { "pid": 0, "total_memory": 1082412, "code_memory": 100, "heap_memory": 64180, "stack_memory": 132, "total_pages": 4, "code_pages": 0, "heap_pages": 0, "stack_pages": 0 }, { "pid": 0, "total_memory": 810676, "code_memory": 44, "heap_memory": 56392, "stack_memory": 132, "total_pages": 4, "code_pages": 0, "heap_pages": 0, "stack_pages": 0 }, { "pid": 0, "total_memory": 466852, "code_memory": 20, "heap_memory": 25952, "stack_memory": 132, "total_pages": 4, "code_pages": 0, "heap_pages": 0, "stack_pages": 0 }, { "pid": 0, "total_memory": 669956, "code_memory": 20, "heap_memory": 50516, "stack_memory": 132, "total_pages": 4, "code_pages": 0, "heap_pages": 0, "stack_pages": 0 }, { "pid": 0, "total_memory": 448368, "code_memory": 8, "heap_memory": 25404, "stack_memory": 132, "total_pages": 4, "code_pages": 0, "heap_pages": 0, "stack_pages": 0 }, { "pid": 0, "total_memory": 679648, "code_memory": 12, "heap_memory": 51504, "stack_memory": 132, "total_pages": 4, "code_pages": 0, "heap_pages": 0, "stack_pages": 0 }, { "pid": 0, "total_memory": 611264, "code_memory": 36, "heap_memory": 43316, "stack_memory": 132, "total_pages": 4, "code_pages": 0, "heap_pages": 0, "stack_pages": 0 }, { "pid": 0, "total_memory": 530796, "code_memory": 8, "heap_memory": 34192, "stack_memory": 132, "total_pages": 4, "code_pages": 0, "heap_pages": 0, "stack_pages": 0 }, { "pid": 0, "total_memory": 672220, "code_memory": 16, "heap_memory": 50556, "stack_memory": 132, "total_pages": 4, "code_pages": 0, "heap_pages": 0, "stack_pages": 0 }, { "pid": 0, "total_memory": 593136, "code_memory": 12, "heap_memory": 38572, "stack_memory": 132, "total_pages": 4, "code_pages": 0, "heap_pages": 0, "stack_pages": 0 }, { "pid": 0, "total_memory": 667144, "code_memory": 28, "heap_memory": 46924, "stack_memory": 132, "total_pages": 4, "code_pages": 0, "heap_pages": 0, "stack_pages": 0 }, { "pid": 0, "total_memory": 70820, "code_memory": 1700, "heap_memory": 480, "stack_memory": 132, "total_pages": 4, "code_pages": 0, "heap_pages": 0, "stack_pages": 0 }, { "pid": 0, "total_memory": 523120, "code_memory": 20, "heap_memory": 27020, "stack_memory": 132, "total_pages": 4, "code_pages": 0, "heap_pages": 0, "stack_pages": 0 }, { "pid": 0, "total_memory": 2837208, "code_memory": 444, "heap_memory": 379108, "stack_memory": 736, "total_pages": 4, "code_pages": 0, "heap_pages": 0, "stack_pages": 0 }, { "pid": 0, "total_memory": 449648, "code_memory": 8, "heap_memory": 25544, "stack_memory": 132, "total_pages": 4, "code_pages": 0, "heap_pages": 0, "stack_pages": 0 }, { "pid": 0, "total_memory": 598572, "code_memory": 76, "heap_memory": 43868, "stack_memory": 132, "total_pages": 4, "code_pages": 0, "heap_pages": 0, "stack_pages": 0 }, { "pid": 0, "total_memory": 1122332, "code_memory": 20, "heap_memory": 89552, "stack_memory": 132, "total_pages": 4, "code_pages": 0, "heap_pages": 0, "stack_pages": 0 }, { "pid": 0, "total_memory": 519120, "code_memory": 72, "heap_memory": 29848, "stack_memory": 132, "total_pages": 4, "code_pages": 0, "heap_pages": 0, "stack_pages": 0 }, { "pid": 0, "total_memory": 449800, "code_memory": 28, "heap_memory": 25940, "stack_memory": 132, "total_pages": 4, "code_pages": 0, "heap_pages": 0, "stack_pages": 0 }, { "pid": 0, "total_memory": 38570844, "code_memory": 110840, "heap_memory": 314780, "stack_memory": 136, "total_pages": 4, "code_pages": 0, "heap_pages": 0, "stack_pages": 0 }, { "pid": 0, "total_memory": 7450844, "code_memory": 98092, "heap_memory": 361044, "stack_memory": 132, "total_pages": 4, "code_pages": 0, "heap_pages": 0, "stack_pages": 0 }, { "pid": 0, "total_memory": 3092332, "code_memory": 8, "heap_memory": 56184, "stack_memory": 132, "total_pages": 4, "code_pages": 0, "heap_pages": 0, "stack_pages": 0 }, { "pid": 0, "total_memory": 821452, "code_memory": 120, "heap_memory": 69116, "stack_memory": 132, "total_pages": 4, "code_pages": 0, "heap_pages": 0, "stack_pages": 0 }, { "pid": 0, "total_memory": 2472, "code_memory": 16, "heap_memory": 204, "stack_memory": 132, "total_pages": 4, "code_pages": 0, "heap_pages": 0, "stack_pages": 0 }, { "pid": 0, "total_memory": 272736, "code_memory": 6520, "heap_memory": 18160, "stack_memory": 132, "total_pages": 4, "code_pages": 0, "heap_pages": 0, "stack_pages": 0 }, { "pid": 0, "total_memory": 600800, "code_memory": 12, "heap_memory": 34556, "stack_memory": 132, "total_pages": 4, "code_pages": 0, "heap_pages": 0, "stack_pages": 0 }, { "pid": 0, "total_memory": 966968, "code_memory": 412, "heap_memory": 77168, "stack_memory": 132, "total_pages": 4, "code_pages": 0, "heap_pages": 0, "stack_pages": 0 }, { "pid": 0, "total_memory": 460492, "code_memory": 98092, "heap_memory": 6324, "stack_memory": 132, "total_pages": 4, "code_pages": 0, "heap_pages": 0, "stack_pages": 0 }, { "pid": 0, "total_memory": 460492, "code_memory": 98092, "heap_memory": 6324, "stack_memory": 132, "total_pages": 4, "code_pages": 0, "heap_pages": 0, "stack_pages": 0 }, { "pid": 0, "total_memory": 2680764, "code_memory": 196, "heap_memory": 232440, "stack_memory": 736, "total_pages": 4, "code_pages": 0, "heap_pages": 0, "stack_pages": 0 }, { "pid": 0, "total_memory": 376048, "code_memory": 4, "heap_memory": 17524, "stack_memory": 132, "total_pages": 4, "code_pages": 0, "heap_pages": 0, "stack_pages": 0 }, { "pid": 0, "total_memory": 466080, "code_memory": 56, "heap_memory": 26496, "stack_memory": 132, "total_pages": 4, "code_pages": 0, "heap_pages": 0, "stack_pages": 0 }, { "pid": 0, "total_memory": 1844848, "code_memory": 8848, "heap_memory": 197444, "stack_memory": 132, "total_pages": 4, "code_pages": 0, "heap_pages": 0, "stack_pages": 0 }, { "pid": 0, "total_memory": 592736, "code_memory": 136, "heap_memory": 38328, "stack_memory": 132, "total_pages": 4, "code_pages": 0, "heap_pages": 0, "stack_pages": 0 }, { "pid": 0, "total_memory": 1827580, "code_memory": 98092, "heap_memory": 157596, "stack_memory": 132, "total_pages": 4, "code_pages": 0, "heap_pages": 0, "stack_pages": 0 }, { "pid": 0, "total_memory": 1186000, "code_memory": 98092, "heap_memory": 90244, "stack_memory": 132, "total_pages": 4, "code_pages": 0, "heap_pages": 0, "stack_pages": 0 }, { "pid": 0, "total_memory": 6059636, "code_memory": 98092, "heap_memory": 157524, "stack_memory": 132, "total_pages": 4, "code_pages": 0, "heap_pages": 0, "stack_pages": 0 }, { "pid": 0, "total_memory": 973028, "code_memory": 98092, "heap_memory": 56984, "stack_memory": 132, "total_pages": 4, "code_pages": 0, "heap_pages": 0, "stack_pages": 0 }, { "pid": 0, "total_memory": 33967112, "code_memory": 110840, "heap_memory": 5652, "stack_memory": 148, "total_pages": 4, "code_pages": 0, "heap_pages": 0, "stack_pages": 0 }, { "pid": 0, "total_memory": 33967100, "code_memory": 110840, "heap_memory": 5652, "stack_memory": 136, "total_pages": 4, "code_pages": 0, "heap_pages": 0, "stack_pages": 0 }, { "pid": 0, "total_memory": 2328300, "code_memory": 356, "heap_memory": 170804, "stack_memory": 736, "total_pages": 4, "code_pages": 0, "heap_pages": 0, "stack_pages": 0 }, { "pid": 0, "total_memory": 527588, "code_memory": 24, "heap_memory": 34244, "stack_memory": 132, "total_pages": 4, "code_pages": 0, "heap_pages": 0, "stack_pages": 0 }, { "pid": 0, "total_memory": 46432, "code_memory": 280, "heap_memory": 476, "stack_memory": 132, "total_pages": 4, "code_pages": 0, "heap_pages": 0, "stack_pages": 0 }, { "pid": 0, "total_memory": 918528, "code_memory": 64, "heap_memory": 127416, "stack_memory": 132, "total_pages": 4, "code_pages": 0, "heap_pages": 0, "stack_pages": 0 }, { "pid": 0, "total_memory": 34185368, "code_memory": 110840, "heap_memory": 203000, "stack_memory": 148, "total_pages": 4, "code_pages": 0, "heap_pages": 0, "stack_pages": 0 }, { "pid": 0, "total_memory": 5929696, "code_memory": 98092, "heap_memory": 170524, "stack_memory": 720, "total_pages": 4, "code_pages": 0, "heap_pages": 0, "stack_pages": 0 }, { "pid": 0, "total_memory": 465160, "code_memory": 98092, "heap_memory": 6936, "stack_memory": 132, "total_pages": 4, "code_pages": 0, "heap_pages": 0, "stack_pages": 0 }, { "pid": 0, "total_memory": 34049328, "code_memory": 110840, "heap_memory": 102228, "stack_memory": 136, "total_pages": 4, "code_pages": 0, "heap_pages": 0, "stack_pages": 0 }, { "pid": 0, "total_memory": 55268640, "code_memory": 110840, "heap_memory": 929068, "stack_memory": 264, "total_pages": 4, "code_pages": 0, "heap_pages": 0, "stack_pages": 0 }, { "pid": 0, "total_memory": 34107368, "code_memory": 110840, "heap_memory": 55628, "stack_memory": 136, "total_pages": 4, "code_pages": 0, "heap_pages": 0, "stack_pages": 0 }, { "pid": 0, "total_memory": 501428, "code_memory": 4, "heap_memory": 66132, "stack_memory": 132, "total_pages": 4, "code_pages": 0, "heap_pages": 0, "stack_pages": 0 }, { "pid": 0, "total_memory": 501428, "code_memory": 4, "heap_memory": 66132, "stack_memory": 132, "total_pages": 4, "code_pages": 0, "heap_pages": 0, "stack_pages": 0 }, { "pid": 0, "total_memory": 225576, "code_memory": 224, "heap_memory": 25272, "stack_memory": 132, "total_pages": 4, "code_pages": 0, "heap_pages": 0, "stack_pages": 0 }, { "pid": 0, "total_memory": 78432, "code_memory": 296, "heap_memory": 8596, "stack_memory": 132, "total_pages": 4, "code_pages": 0, "heap_pages": 0, "stack_pages": 0 }, { "pid": 0, "total_memory": 225576, "code_memory": 224, "heap_memory": 25272, "stack_memory": 132, "total_pages": 4, "code_pages": 0, "heap_pages": 0, "stack_pages": 0 }, { "pid": 0, "total_memory": 78432, "code_memory": 296, "heap_memory": 8596, "stack_memory": 132, "total_pages": 4, "code_pages": 0, "heap_pages": 0, "stack_pages": 0 }, { "pid": 0, "total_memory": 78432, "code_memory": 296, "heap_memory": 8596, "stack_memory": 132, "total_pages": 4, "code_pages": 0, "heap_pages": 0, "stack_pages": 0 }, { "pid": 0, "total_memory": 1177822752, "code_memory": 117736, "heap_memory": 494496, "stack_memory": 132, "total_pages": 4, "code_pages": 0, "heap_pages": 0, "stack_pages": 0 }, { "pid": 0, "total_memory": 34023036, "code_memory": 117736, "heap_memory": 4740, "stack_memory": 148, "total_pages": 4, "code_pages": 0, "heap_pages": 0, "stack_pages": 0 }, { "pid": 0, "total_memory": 34023020, "code_memory": 117736, "heap_memory": 4780, "stack_memory": 132, "total_pages": 4, "code_pages": 0, "heap_pages": 0, "stack_pages": 0 }, { "pid": 0, "total_memory": 34023044, "code_memory": 117736, "heap_memory": 4828, "stack_memory": 156, "total_pages": 4, "code_pages": 0, "heap_pages": 0, "stack_pages": 0 }, { "pid": 0, "total_memory": 33594176, "code_memory": 968, "heap_memory": 30628, "stack_memory": 132, "total_pages": 4, "code_pages": 0, "heap_pages": 0, "stack_pages": 0 }, { "pid": 0, "total_memory": 34490492, "code_memory": 117736, "heap_memory": 283260, "stack_memory": 148, "total_pages": 4, "code_pages": 0, "heap_pages": 0, "stack_pages": 0 }, { "pid": 0, "total_memory": 34089596, "code_memory": 117736, "heap_memory": 80364, "stack_memory": 132, "total_pages": 4, "code_pages": 0, "heap_pages": 0, "stack_pages": 0 }, { "pid": 0, "total_memory": 1190267984, "code_memory": 117736, "heap_memory": 816624, "stack_memory": 188, "total_pages": 4, "code_pages": 0, "heap_pages": 0, "stack_pages": 0 }, { "pid": 0, "total_memory": 1177602348, "code_memory": 117736, "heap_memory": 216528, "stack_memory": 132, "total_pages": 4, "code_pages": 0, "heap_pages": 0, "stack_pages": 0 }, { "pid": 0, "total_memory": 1177701208, "code_memory": 117736, "heap_memory": 248084, "stack_memory": 132, "total_pages": 4, "code_pages": 0, "heap_pages": 0, "stack_pages": 0 }, { "pid": 0, "total_memory": 1188102608, "code_memory": 117736, "heap_memory": 239824, "stack_memory": 156, "total_pages": 4, "code_pages": 0, "heap_pages": 0, "stack_pages": 0 }, { "pid": 0, "total_memory": 601460, "code_memory": 16, "heap_memory": 42428, "stack_memory": 132, "total_pages": 4, "code_pages": 0, "heap_pages": 0, "stack_pages": 0 }, { "pid": 0, "total_memory": 529332, "code_memory": 16, "heap_memory": 34020, "stack_memory": 132, "total_pages": 4, "code_pages": 0, "heap_pages": 0, "stack_pages": 0 }, { "pid": 0, "total_memory": 528964, "code_memory": 16, "heap_memory": 35636, "stack_memory": 132, "total_pages": 4, "code_pages": 0, "heap_pages": 0, "stack_pages": 0 }, { "pid": 0, "total_memory": 2217232, "code_memory": 812, "heap_memory": 231332, "stack_memory": 732, "total_pages": 4, "code_pages": 0, "heap_pages": 0, "stack_pages": 0 }, { "pid": 0, "total_memory": 464148, "code_memory": 20, "heap_memory": 25776, "stack_memory": 132, "total_pages": 4, "code_pages": 0, "heap_pages": 0, "stack_pages": 0 }, { "pid": 0, "total_memory": 578028, "code_memory": 48, "heap_memory": 46792, "stack_memory": 132, "total_pages": 4, "code_pages": 0, "heap_pages": 0, "stack_pages": 0 }, { "pid": 0, "total_memory": 578028, "code_memory": 48, "heap_memory": 46792, "stack_memory": 132, "total_pages": 4, "code_pages": 0, "heap_pages": 0, "stack_pages": 0 }, { "pid": 0, "total_memory": 578028, "code_memory": 48, "heap_memory": 46792, "stack_memory": 132, "total_pages": 4, "code_pages": 0, "heap_pages": 0, "stack_pages": 0 }, { "pid": 0, "total_memory": 269996, "code_memory": 104, "heap_memory": 31544, "stack_memory": 132, "total_pages": 4, "code_pages": 0, "heap_pages": 0, "stack_pages": 0 }, { "pid": 0, "total_memory": 34525544, "code_memory": 180068, "heap_memory": 546696, "stack_memory": 132, "total_pages": 4, "code_pages": 0, "heap_pages": 0, "stack_pages": 0 }, { "pid": 0, "total_memory": 221460, "code_memory": 16, "heap_memory": 340, "stack_memory": 132, "total_pages": 4, "code_pages": 0, "heap_pages": 0, "stack_pages": 0 }, { "pid": 0, "total_memory": 221460, "code_memory": 16, "heap_memory": 340, "stack_memory": 132, "total_pages": 4, "code_pages": 0, "heap_pages": 0, "stack_pages": 0 }, { "pid": 0, "total_memory": 4604, "code_memory": 8, "heap_memory": 236, "stack_memory": 132, "total_pages": 4, "code_pages": 0, "heap_pages": 0, "stack_pages": 0 }, { "pid": 0, "total_memory": 33576664, "code_memory": 1008, "heap_memory": 17040, "stack_memory": 132, "total_pages": 4, "code_pages": 0, "heap_pages": 0, "stack_pages": 0 }, { "pid": 0, "total_memory": 33567428, "code_memory": 1008, "heap_memory": 8600, "stack_memory": 132, "total_pages": 4, "code_pages": 0, "heap_pages": 0, "stack_pages": 0 }, { "pid": 0, "total_memory": 34402444, "code_memory": 180068, "heap_memory": 61172, "stack_memory": 144, "total_pages": 4, "code_pages": 0, "heap_pages": 0, "stack_pages": 0 }, { "pid": 0, "total_memory": 34402432, "code_memory": 180068, "heap_memory": 61212, "stack_memory": 132, "total_pages": 4, "code_pages": 0, "heap_pages": 0, "stack_pages": 0 }, { "pid": 0, "total_memory": 34402460, "code_memory": 180068, "heap_memory": 61212, "stack_memory": 160, "total_pages": 4, "code_pages": 0, "heap_pages": 0, "stack_pages": 0 }, { "pid": 0, "total_memory": 34853768, "code_memory": 180068, "heap_memory": 395824, "stack_memory": 148, "total_pages": 4, "code_pages": 0, "heap_pages": 0, "stack_pages": 0 }, { "pid": 0, "total_memory": 34174160, "code_memory": 180068, "heap_memory": 150020, "stack_memory": 132, "total_pages": 4, "code_pages": 0, "heap_pages": 0, "stack_pages": 0 }, { "pid": 0, "total_memory": 34461768, "code_memory": 180068, "heap_memory": 138016, "stack_memory": 160, "total_pages": 4, "code_pages": 0, "heap_pages": 0, "stack_pages": 0 }, { "pid": 0, "total_memory": 1186730340, "code_memory": 180068, "heap_memory": 281092, "stack_memory": 160, "total_pages": 4, "code_pages": 0, "heap_pages": 0, "stack_pages": 0 }, { "pid": 0, "total_memory": 34206508, "code_memory": 180068, "heap_memory": 75732, "stack_memory": 132, "total_pages": 4, "code_pages": 0, "heap_pages": 0, "stack_pages": 0 }, { "pid": 0, "total_memory": 1186753508, "code_memory": 180068, "heap_memory": 355484, "stack_memory": 192, "total_pages": 4, "code_pages": 0, "heap_pages": 0, "stack_pages": 0 }, { "pid": 0, "total_memory": 1186748900, "code_memory": 180068, "heap_memory": 293980, "stack_memory": 160, "total_pages": 4, "code_pages": 0, "heap_pages": 0, "stack_pages": 0 }, { "pid": 0, "total_memory": 1186732320, "code_memory": 180068, "heap_memory": 195556, "stack_memory": 160, "total_pages": 4, "code_pages": 0, "heap_pages": 0, "stack_pages": 0 }, { "pid": 0, "total_memory": 1188893800, "code_memory": 180068, "heap_memory": 220168, "stack_memory": 160, "total_pages": 4, "code_pages": 0, "heap_pages": 0, "stack_pages": 0 }, { "pid": 0, "total_memory": 1188893800, "code_memory": 180068, "heap_memory": 220168, "stack_memory": 160, "total_pages": 4, "code_pages": 0, "heap_pages": 0, "stack_pages": 0 }, { "pid": 0, "total_memory": 1177619240, "code_memory": 117736, "heap_memory": 143056, "stack_memory": 132, "total_pages": 4, "code_pages": 0, "heap_pages": 0, "stack_pages": 0 }, { "pid": 0, "total_memory": 1177604056, "code_memory": 117736, "heap_memory": 259000, "stack_memory": 1008, "total_pages": 4, "code_pages": 0, "heap_pages": 0, "stack_pages": 0 }, { "pid": 0, "total_memory": 101620, "code_memory": 21968, "heap_memory": 78604, "stack_memory": 132, "total_pages": 4, "code_pages": 0, "heap_pages": 0, "stack_pages": 0 }, { "pid": 0, "total_memory": 224764, "code_memory": 908, "heap_memory": 2104, "stack_memory": 132, "total_pages": 4, "code_pages": 0, "heap_pages": 0, "stack_pages": 0 }, { "pid": 0, "total_memory": 225192, "code_memory": 908, "heap_memory": 2216, "stack_memory": 132, "total_pages": 4, "code_pages": 0, "heap_pages": 0, "stack_pages": 0 }, { "pid": 0, "total_memory": 4269048, "code_memory": 12444, "heap_memory": 66164, "stack_memory": 132, "total_pages": 4, "code_pages": 0, "heap_pages": 0, "stack_pages": 0 }, { "pid": 0, "total_memory": 4269048, "code_memory": 12444, "heap_memory": 66164, "stack_memory": 132, "total_pages": 4, "code_pages": 0, "heap_pages": 0, "stack_pages": 0 }, { "pid": 0, "total_memory": 4269048, "code_memory": 12444, "heap_memory": 66164, "stack_memory": 132, "total_pages": 4, "code_pages": 0, "heap_pages": 0, "stack_pages": 0 }, { "pid": 0, "total_memory": 4269048, "code_memory": 12444, "heap_memory": 66164, "stack_memory": 132, "total_pages": 4, "code_pages": 0, "heap_pages": 0, "stack_pages": 0 }, { "pid": 0, "total_memory": 4269048, "code_memory": 12444, "heap_memory": 66164, "stack_memory": 132, "total_pages": 4, "code_pages": 0, "heap_pages": 0, "stack_pages": 0 }, { "pid": 0, "total_memory": 4269048, "code_memory": 12444, "heap_memory": 66164, "stack_memory": 132, "total_pages": 4, "code_pages": 0, "heap_pages": 0, "stack_pages": 0 }, { "pid": 0, "total_memory": 907928, "code_memory": 212, "heap_memory": 69788, "stack_memory": 180, "total_pages": 4, "code_pages": 0, "heap_pages": 0, "stack_pages": 0 }, { "pid": 0, "total_memory": 907928, "code_memory": 212, "heap_memory": 69788, "stack_memory": 180, "total_pages": 4, "code_pages": 0, "heap_pages": 0, "stack_pages": 0 }, { "pid": 0, "total_memory": 907928, "code_memory": 212, "heap_memory": 69788, "stack_memory": 180, "total_pages": 4, "code_pages": 0, "heap_pages": 0, "stack_pages": 0 }, { "pid": 0, "total_memory": 4268832, "code_memory": 12444, "heap_memory": 65948, "stack_memory": 132, "total_pages": 4, "code_pages": 0, "heap_pages": 0, "stack_pages": 0 }, { "pid": 0, "total_memory": 4268832, "code_memory": 12444, "heap_memory": 65948, "stack_memory": 132, "total_pages": 4, "code_pages": 0, "heap_pages": 0, "stack_pages": 0 }, { "pid": 0, "total_memory": 1177319836, "code_memory": 117736, "heap_memory": 70416, "stack_memory": 132, "total_pages": 4, "code_pages": 0, "heap_pages": 0, "stack_pages": 0 }, { "pid": 0, "total_memory": 1177319836, "code_memory": 117736, "heap_memory": 70416, "stack_memory": 132, "total_pages": 4, "code_pages": 0, "heap_pages": 0, "stack_pages": 0 }, { "pid": 0, "total_memory": 1177319836, "code_memory": 117736, "heap_memory": 70416, "stack_memory": 132, "total_pages": 4, "code_pages": 0, "heap_pages": 0, "stack_pages": 0 }, { "pid": 0, "total_memory": 225192, "code_memory": 908, "heap_memory": 2216, "stack_memory": 132, "total_pages": 4, "code_pages": 0, "heap_pages": 0, "stack_pages": 0 }, { "pid": 0, "total_memory": 225192, "code_memory": 908, "heap_memory": 2216, "stack_memory": 132, "total_pages": 4, "code_pages": 0, "heap_pages": 0, "stack_pages": 0 }, { "pid": 0, "total_memory": 225192, "code_memory": 908, "heap_memory": 2216, "stack_memory": 132, "total_pages": 4, "code_pages": 0, "heap_pages": 0, "stack_pages": 0 }, { "pid": 0, "total_memory": 225192, "code_memory": 908, "heap_memory": 2216, "stack_memory": 132, "total_pages": 4, "code_pages": 0, "heap_pages": 0, "stack_pages": 0 }, { "pid": 0, "total_memory": 225192, "code_memory": 908, "heap_memory": 2216, "stack_memory": 132, "total_pages": 4, "code_pages": 0, "heap_pages": 0, "stack_pages": 0 }, { "pid": 0, "total_memory": 225192, "code_memory": 908, "heap_memory": 2216, "stack_memory": 132, "total_pages": 4, "code_pages": 0, "heap_pages": 0, "stack_pages": 0 }, { "pid": 0, "total_memory": 225192, "code_memory": 908, "heap_memory": 2216, "stack_memory": 132, "total_pages": 4, "code_pages": 0, "heap_pages": 0, "stack_pages": 0 }, { "pid": 0, "total_memory": 225192, "code_memory": 908, "heap_memory": 2216, "stack_memory": 132, "total_pages": 4, "code_pages": 0, "heap_pages": 0, "stack_pages": 0 }, { "pid": 0, "total_memory": 225192, "code_memory": 908, "heap_memory": 2216, "stack_memory": 132, "total_pages": 4, "code_pages": 0, "heap_pages": 0, "stack_pages": 0 }, { "pid": 0, "total_memory": 225192, "code_memory": 908, "heap_memory": 2216, "stack_memory": 132, "total_pages": 4, "code_pages": 0, "heap_pages": 0, "stack_pages": 0 }, { "pid": 0, "total_memory": 225192, "code_memory": 908, "heap_memory": 2216, "stack_memory": 132, "total_pages": 4, "code_pages": 0, "heap_pages": 0, "stack_pages": 0 }, { "pid": 0, "total_memory": 225192, "code_memory": 908, "heap_memory": 2216, "stack_memory": 132, "total_pages": 4, "code_pages": 0, "heap_pages": 0, "stack_pages": 0 }, { "pid": 0, "total_memory": 225192, "code_memory": 908, "heap_memory": 2216, "stack_memory": 132, "total_pages": 4, "code_pages": 0, "heap_pages": 0, "stack_pages": 0 }, { "pid": 0, "total_memory": 225192, "code_memory": 908, "heap_memory": 2216, "stack_memory": 132, "total_pages": 4, "code_pages": 0, "heap_pages": 0, "stack_pages": 0 }, { "pid": 0, "total_memory": 225192, "code_memory": 908, "heap_memory": 2216, "stack_memory": 132, "total_pages": 4, "code_pages": 0, "heap_pages": 0, "stack_pages": 0 }, { "pid": 0, "total_memory": 2063304, "code_memory": 276, "heap_memory": 263248, "stack_memory": 732, "total_pages": 4, "code_pages": 0, "heap_pages": 0, "stack_pages": 0 }, { "pid": 0, "total_memory": 1188947808, "code_memory": 180068, "heap_memory": 641352, "stack_memory": 164, "total_pages": 4, "code_pages": 0, "heap_pages": 0, "stack_pages": 0 }, { "pid": 0, "total_memory": 1188947808, "code_memory": 180068, "heap_memory": 641352, "stack_memory": 164, "total_pages": 4, "code_pages": 0, "heap_pages": 0, "stack_pages": 0 }, { "pid": 0, "total_memory": 1188947808, "code_memory": 180068, "heap_memory": 641352, "stack_memory": 164, "total_pages": 4, "code_pages": 0, "heap_pages": 0, "stack_pages": 0 }, { "pid": 0, "total_memory": 1186751484, "code_memory": 180068, "heap_memory": 273172, "stack_memory": 160, "total_pages": 4, "code_pages": 0, "heap_pages": 0, "stack_pages": 0 }, { "pid": 0, "total_memory": 42841668, "code_memory": 180068, "heap_memory": 113372, "stack_memory": 160, "total_pages": 4, "code_pages": 0, "heap_pages": 0, "stack_pages": 0 }, { "pid": 0, "total_memory": 1186770168, "code_memory": 180068, "heap_memory": 392156, "stack_memory": 168, "total_pages": 4, "code_pages": 0, "heap_pages": 0, "stack_pages": 0 }, { "pid": 0, "total_memory": 1186770168, "code_memory": 180068, "heap_memory": 392156, "stack_memory": 168, "total_pages": 4, "code_pages": 0, "heap_pages": 0, "stack_pages": 0 }, { "pid": 0, "total_memory": 1186770168, "code_memory": 180068, "heap_memory": 392156, "stack_memory": 168, "total_pages": 4, "code_pages": 0, "heap_pages": 0, "stack_pages": 0 }, { "pid": 0, "total_memory": 16700, "code_memory": 12, "heap_memory": 516, "stack_memory": 132, "total_pages": 4, "code_pages": 0, "heap_pages": 0, "stack_pages": 0 }, { "pid": 0, "total_memory": 16700, "code_memory": 12, "heap_memory": 516, "stack_memory": 132, "total_pages": 4, "code_pages": 0, "heap_pages": 0, "stack_pages": 0 }, { "pid": 0, "total_memory": 16700, "code_memory": 12, "heap_memory": 516, "stack_memory": 132, "total_pages": 4, "code_pages": 0, "heap_pages": 0, "stack_pages": 0 }, { "pid": 0, "total_memory": 1186680516, "code_memory": 180068, "heap_memory": 133016, "stack_memory": 160, "total_pages": 4, "code_pages": 0, "heap_pages": 0, "stack_pages": 0 }, { "pid": 0, "total_memory": 236536, "code_memory": 128, "heap_memory": 1204, "stack_memory": 136, "total_pages": 4, "code_pages": 0, "heap_pages": 0, "stack_pages": 0 }, { "pid": 0, "total_memory": 511328, "code_memory": 60, "heap_memory": 81756, "stack_memory": 132, "total_pages": 4, "code_pages": 0, "heap_pages": 0, "stack_pages": 0 }, { "pid": 0, "total_memory": 511328, "code_memory": 60, "heap_memory": 81756, "stack_memory": 132, "total_pages": 4, "code_pages": 0, "heap_pages": 0, "stack_pages": 0 }, { "pid": 0, "total_memory": 511328, "code_memory": 60, "heap_memory": 81756, "stack_memory": 132, "total_pages": 4, "code_pages": 0, "heap_pages": 0, "stack_pages": 0 }, { "pid": 0, "total_memory": 3068, "code_memory": 4, "heap_memory": 748, "stack_memory": 132, "total_pages": 4, "code_pages": 0, "heap_pages": 0, "stack_pages": 0 } ]